pydipapi/__init__.py
pydipapi/api.py
pydipapi/async_api.py
pydipapi/openapi.yaml
pydipapi/py.typed
pydipapi/type.py
pydipapi/client/__init__.py
pydipapi/client/async_client.py
pydipapi/client/base_client.py
pydipapi/parsers/__init__.py
pydipapi/parsers/activity_parser.py
pydipapi/parsers/base_parser.py
pydipapi/parsers/document_parser.py
pydipapi/parsers/person_parser.py
pydipapi/parsers/protocol_parser.py
pydipapi/util/__init__.py
pydipapi/util/cache.py
pydipapi/util/error_handler.py
pydipapi/util/error_handling.py
pydipapi-0.1.1.dist-info/licenses/LICENSE
pydipapi-0.1.1.dist-info/METADATA
pydipapi-0.1.1.dist-info/WHEEL
pydipapi-0.1.1.dist-info/top_level.txt
pydipapi-0.1.1.dist-info/RECORD
