Metadata-Version: 2.4
Name: pydipapi
Version: 0.1.1
Summary: Modern Python client for the German Bundestag API with batch operations, caching, and performance optimization
Author-email: Johannes Gegenheimer <jg@politikpraxis.de>
Maintainer-email: Johannes Gegenheimer <jg@politikpraxis.de>
License-Expression: MIT
Project-URL: Homepage, https://github.com/lichtbaer/pydipapi
Project-URL: Documentation, https://lichtbaer.github.io/pydipapi/
Project-URL: Repository, https://github.com/lichtbaer/pydipapi.git
Project-URL: Bug Tracker, https://github.com/lichtbaer/pydipapi/issues
Project-URL: Changelog, https://lichtbaer.github.io/pydipapi/changelog/
Project-URL: API Reference, https://lichtbaer.github.io/pydipapi/api_reference/
Keywords: bundestag,api,parliament,politics,germany,government,data,political-science
Classifier: Development Status :: 4 - Beta
Classifier: Intended Audience :: Developers
Classifier: Intended Audience :: Science/Research
Classifier: Intended Audience :: Education
Classifier: Operating System :: OS Independent
Classifier: Programming Language :: Python :: 3
Classifier: Programming Language :: Python :: 3.8
Classifier: Programming Language :: Python :: 3.9
Classifier: Programming Language :: Python :: 3.10
Classifier: Programming Language :: Python :: 3.11
Classifier: Programming Language :: Python :: 3.12
Classifier: Topic :: Internet :: WWW/HTTP :: Dynamic Content
Classifier: Topic :: Scientific/Engineering :: Information Analysis
Classifier: Topic :: Software Development :: Libraries :: Python Modules
Classifier: Topic :: Sociology
Requires-Python: >=3.8
License-File: LICENSE
Requires-Dist: requests>=2.25.0
Requires-Dist: pydantic>=1.8.0
Provides-Extra: dev
Requires-Dist: pytest>=6.0; extra == "dev"
Requires-Dist: pytest-cov>=4.0.0; extra == "dev"
Requires-Dist: ruff>=0.4.0; extra == "dev"
Requires-Dist: bandit>=1.7.0; extra == "dev"
Requires-Dist: mypy>=1.0.0; extra == "dev"
Requires-Dist: build>=0.10.0; extra == "dev"
Requires-Dist: twine>=4.0.0; extra == "dev"
Requires-Dist: mkdocs>=1.5.0; extra == "dev"
Requires-Dist: mkdocs-material>=9.0.0; extra == "dev"
Requires-Dist: mkdocstrings[python]>=0.20.0; extra == "dev"
Requires-Dist: pre-commit>=3.0.0; extra == "dev"
Requires-Dist: jupyter>=1.0.0; extra == "dev"
Requires-Dist: jupyterlab>=3.0.0; extra == "dev"
Provides-Extra: docs
Requires-Dist: mkdocs>=1.5.0; extra == "docs"
Requires-Dist: mkdocs-material>=9.0.0; extra == "docs"
Requires-Dist: mkdocstrings[python]>=0.20.0; extra == "docs"
Provides-Extra: notebooks
Requires-Dist: jupyter>=1.0.0; extra == "notebooks"
Requires-Dist: jupyterlab>=3.0.0; extra == "notebooks"
Dynamic: license-file
